Dockerfile
HISTORY.md
LICENSE.txt
MANIFEST.in
README.md
VERSION.txt
requirements.txt
setup.py
workflow.cwl
TargQC.egg-info/PKG-INFO
TargQC.egg-info/SOURCES.txt
TargQC.egg-info/dependency_links.txt
TargQC.egg-info/not-zip-safe
TargQC.egg-info/requires.txt
TargQC.egg-info/top_level.txt
bed_venn/__init__.py
bed_venn/venn.py
ensembl/__init__.py
ensembl/bed_annotation.py
ensembl/canon_cancer_replacement.txt
ensembl/generate_cds_bed.py
ensembl/generate_ensembl_data.py
ensembl/hg19/canon_transcripts_hg19_ensembl.txt
ensembl/hg19/ensembl.bed.gz
ensembl/hg19/ensembl.bed.gz.tbi
ensembl/hg38/canon_transcripts_hg38_ensembl.txt
ensembl/hg38/ensembl.bed.gz
ensembl/hg38/ensembl.bed.gz.tbi
ensembl/mm10/ensembl.bed.gz
ensembl/mm10/ensembl.bed.gz.tbi
scripts/annotate_bed.py
scripts/bed_venn.py
scripts/targqc
targqc/.DS_Store
targqc/Target.py
targqc/__init__.py
targqc/config.py
targqc/fastq.py
targqc/general_report.py
targqc/prep_bed.py
targqc/region_coverage.py
targqc/summarize.py
targqc/version.py
targqc/gender/chrY.hg19.bed
targqc/gender/chrY.hg38.bed
targqc/qualimap/.DS_Store
targqc/qualimap/__init__.py
targqc/qualimap/report_parser.py
targqc/qualimap/runner.py
tests/__init__.py
tests/test.py
tests/test_annotate_bed.py
tests/test_travis.py