Metadata-Version: 1.1
Name: TargQC
Version: 1.5.2
Summary: Genome capture target coverage evaluation tool
Home-page: https://github.com/vladsaveliev/TargQC
Author: Vlad Saveliev and Alla Mikheenko
Author-email: vladislav.sav@gmail.com
License: GPLv3
Download-URL: https://github.com/vladsaveliev/TargQC/releases
Keywords: bioinformatics
Platform: UNKNOWN
Classifier: Environment :: Console
Classifier: Environment :: Web Environment
Classifier: Intended Audience :: Science/Research
Classifier: License :: OSI Approved :: GNU General Public License v3 (GPLv3)
Classifier: Natural Language :: English
Classifier: Operating System :: MacOS :: MacOS X
Classifier: Operating System :: POSIX
Classifier: Operating System :: Unix
Classifier: Programming Language :: Python
Classifier: Programming Language :: JavaScript
Classifier: Topic :: Scientific/Engineering
Classifier: Topic :: Scientific/Engineering :: Bio-Informatics
